settings_doc/__init__.py
settings_doc/importing.py
settings_doc/main.py
settings_doc/template_functions.py
settings_doc/templates/debug.jinja
settings_doc/templates/dotenv.jinja
settings_doc/templates/markdown.jinja
settings_doc-4.3.2.dist-info/LICENSE
settings_doc-4.3.2.dist-info/METADATA
settings_doc-4.3.2.dist-info/WHEEL
settings_doc-4.3.2.dist-info/entry_points.txt
settings_doc-4.3.2.dist-info/RECORD
