Metadata-Version: 2.1
Name: settings-doc
Version: 4.3.2
Summary: A command line tool for generating Markdown documentation and .env files from pydantic BaseSettings.
Home-page: https://github.com/radeklat/settings-doc
License: MIT
Keywords: documentation,environment variables,generated,markdown,BaseSettings
Author: Radek Lát
Author-email: radek.lat@gmail.com
Requires-Python: >=3.8.1,<4.0.0
Classifier: Development Status :: 5 - Production/Stable
Classifier: Environment :: Console
Classifier: Framework :: Pydantic :: 2
Classifier: Intended Audience :: Developers
Classifier: Intended Audience :: System Administrators
Classifier: License :: OSI Approved :: MIT License
Classifier: Operating System :: OS Independent
Classifier: Programming Language :: Python :: 3
Classifier: Programming Language :: Python :: 3.9
Classifier: Programming Language :: Python :: 3.10
Classifier: Programming Language :: Python :: 3.11
Classifier: Programming Language :: Python :: 3.12
Classifier: Programming Language :: Python :: 3.8
Classifier: Topic :: Documentation
Classifier: Topic :: Software Development
Classifier: Topic :: Software Development :: Documentation
Classifier: Topic :: System :: Installation/Setup
Classifier: Topic :: System :: Software Distribution
Classifier: Topic :: System :: Systems Administration
Classifier: Topic :: Text Processing :: Markup :: Markdown
Classifier: Topic :: Utilities
Classifier: Typing :: Typed
Requires-Dist: Jinja2 (>=3.0.2,<4.0.0)
Requires-Dist: click (>=8.0,<9.0)
Requires-Dist: pydantic (>=2.3,<3.0)
Requires-Dist: pydantic-settings (>=2.0.3,<3.0.0)
